smart_mem_cache/__init__.py
smart_mem_cache/llm_caller.py
smart_mem_cache/smart_mem_cache.py
smart_cache_package-0.1.1.dist-info/LICENSE
smart_cache_package-0.1.1.dist-info/METADATA
smart_cache_package-0.1.1.dist-info/WHEEL
smart_cache_package-0.1.1.dist-info/top_level.txt
smart_cache_package-0.1.1.dist-info/RECORD
