Metadata-Version: 2.1
Name: smart_cache_package
Version: 0.1.1
Summary: An intelligent caching and LLM routing package using Mem0AI and zero-shot classification.
Home-page: https://github.com/nichurocks02/smart_cache_package.git
Author: Nishkal Gupta M
Author-email: nishkalrocks02@gmail.com
Classifier: Programming Language :: Python :: 3
Classifier: Operating System :: OS Independent
Classifier: License :: OSI Approved :: MIT License
Requires-Python: >=3.10
License-File: LICENSE
Requires-Dist: mem0AI
Requires-Dist: transformers
Requires-Dist: openai
